{
  "definitions": [
    {
      "interface": {
        "name": "HTMLMediaElement",
        "inherits": null,
        "partial": true,
        "extended_attributes": [
        ],
        "members": [
          {
            "attribute": {
              "name": "sinkId",
              "type": "DOMString",
              "readonly": true,
              "static": false,
              "stringifier": false,
              "inherit": false,
              "extended_attributes": [
                {
                  "name": "SecureContext",
                  "value": null
                }
              ]
            }
          },
          {
            "operation": {
              "name": "setSinkId",
              "return_type": {
                "promise": "undefined"
              },
              "arguments": [
                {
                  "name": "sinkId",
                  "type": "DOMString",
                  "optional": false,
                  "variadic": false,
                  "default_value": null,
                  "extended_attributes": [
                  ]
                }
              ],
              "static": false,
              "special": null,
              "extended_attributes": [
                {
                  "name": "SecureContext",
                  "value": null
                }
              ]
            }
          }
        ]
      }
    },
    {
      "interface": {
        "name": "MediaDevices",
        "inherits": null,
        "partial": true,
        "extended_attributes": [
        ],
        "members": [
          {
            "operation": {
              "name": "selectAudioOutput",
              "return_type": {
                "promise": {
                  "identifier": "MediaDeviceInfo"
                }
              },
              "arguments": [
                {
                  "name": "options",
                  "type": {
                    "identifier": "AudioOutputOptions"
                  },
                  "optional": true,
                  "variadic": false,
                  "default_value": {},
                  "extended_attributes": [
                  ]
                }
              ],
              "static": false,
              "special": null,
              "extended_attributes": [
              ]
            }
          }
        ]
      }
    },
    {
      "dictionary": {
        "name": "AudioOutputOptions",
        "inherits": null,
        "partial": false,
        "extended_attributes": [
        ],
        "members": [
          {
            "name": "deviceId",
            "type": "DOMString",
            "required": false,
            "default_value": "",
            "extended_attributes": [
            ]
          }
        ]
      }
    }
  ]
}
